pypush/_version.py
pypush/apns/__init__.py
pypush/apns/_protocol.py
pypush/apns/_util.py
pypush/apns/albert.py
pypush/apns/filters.py
pypush/apns/lifecycle.py
pypush/apns/protocol.py
pypush/apns/transport.py
pypush/cli/__init__.py
pypush/cli/_frida.py
pypush/cli/proxy.py
pypush/cloudkit/.gitkeep
pypush/grandslam/.gitkeep
pypush/ids/.gitkeep
pypush/imessage/.gitkeep
pypush-2.0.1.dist-info/licenses/LICENSE
pypush-2.0.1.dist-info/METADATA
pypush-2.0.1.dist-info/WHEEL
pypush-2.0.1.dist-info/entry_points.txt
pypush-2.0.1.dist-info/top_level.txt
pypush-2.0.1.dist-info/RECORD
