Metadata-Version: 2.4
Name: pypush
Version: 2.0.1
Summary: Interact with Apple Private API
Author-email: JJTech <jjtech@jjtech.dev>
License: Server Side Public License (SSPL)
Project-URL: Homepage, https://github.com/JJTech0130/pypush
Project-URL: Issues, https://github.com/JJTech0130/pypush/issues
Keywords: apple,api,reverse engineering,imessage,apns
Classifier: Programming Language :: Python :: 3
Classifier: Development Status :: 3 - Alpha
Classifier: Operating System :: OS Independent
Classifier: License :: Other/Proprietary License
Requires-Python: >=3.9
License-File: LICENSE
Requires-Dist: anyio
Requires-Dist: httpx[http2]
Requires-Dist: cryptography
Requires-Dist: typing-extensions
Requires-Dist: exceptiongroup
Requires-Dist: importlib_metadata; python_version >= "3.9"
Provides-Extra: test
Requires-Dist: pytest; extra == "test"
Requires-Dist: pytest-asyncio; extra == "test"
Provides-Extra: cli
Requires-Dist: frida; extra == "cli"
Requires-Dist: rich; extra == "cli"
Requires-Dist: typer; extra == "cli"
Dynamic: license-file
